vegindex/__init__.py
vegindex/config.py
vegindex/gcctimeseries.py
vegindex/generate_ndvi_summary_timeseries.py
vegindex/generate_ndvi_timeseries.py
vegindex/generate_roi_ir_timeseries.py
vegindex/generate_roi_timeseries.py
vegindex/generate_summary_timeseries.py
vegindex/ir_roitimeseries.py
vegindex/ndvi_summary_timeseries.py
vegindex/ndvitimeseries.py
vegindex/plot_roistats.py
vegindex/quantile.py
vegindex/roilist.py
vegindex/roimask.py
vegindex/roitimeseries.py
vegindex/update_ndvi_summary_timeseries.py
vegindex/update_roi_ir_timeseries.py
vegindex/update_roi_timeseries.py
vegindex/update_summary_timeseries.py
vegindex/utils.py
vegindex/vegindex.py
vegindex-0.10.2.dist-info/AUTHORS.rst
vegindex-0.10.2.dist-info/LICENSE
vegindex-0.10.2.dist-info/METADATA
vegindex-0.10.2.dist-info/WHEEL
vegindex-0.10.2.dist-info/entry_points.txt
vegindex-0.10.2.dist-info/top_level.txt
vegindex-0.10.2.dist-info/RECORD
