Metadata-Version: 2.1
Name: vegindex
Version: 0.10.2
Summary: Python tools for generating vegetation index timeseries from PhenoCam images.
Home-page: https://github.com/tmilliman/python-vegindex/
Author: Thomas Milliman
Author-email: thomas.milliman@unh.edu
License: MIT
Keywords: phenology,phenocam,vegetation,index
Platform: UNKNOWN
Classifier: Development Status :: 4 - Beta
Classifier: Intended Audience :: Science/Research
Classifier: License :: OSI Approved :: MIT License
Classifier: Operating System :: Unix
Classifier: Operating System :: POSIX
Classifier: Operating System :: Microsoft :: Windows
Classifier: Programming Language :: Python
Classifier: Programming Language :: Python :: 3
Classifier: Programming Language :: Python :: 3.6
Classifier: Programming Language :: Python :: 3.7
Classifier: Programming Language :: Python :: 3.8
Classifier: Programming Language :: Python :: 3.9
Classifier: Topic :: Scientific/Engineering :: Bio-Informatics
License-File: LICENSE
License-File: AUTHORS.rst
Requires-Dist: matplotlib
Requires-Dist: Pillow
Requires-Dist: pyephem
Requires-Dist: requests
Requires-Dist: numpy
Requires-Dist: pandas
Provides-Extra: rst
Requires-Dist: docutils ; extra == 'rst'
